smooch/__init__.py
smooch/app_users.py
smooch/authentication.py
smooch/conversations.py
smooch/endpoint.py
smooch/exceptions.py
smooch/webhooks.py
smooch/parse/__init__.py
smooch/parse/webook.py
python_smooch-1.0.4.dist-info/LICENSE
python_smooch-1.0.4.dist-info/METADATA
python_smooch-1.0.4.dist-info/WHEEL
python_smooch-1.0.4.dist-info/top_level.txt
python_smooch-1.0.4.dist-info/RECORD
