Metadata-Version: 2.1
Name: python-smooch
Version: 1.0.4
Summary: A Python wrapper for the Smooch API
Home-page: https://devinmcgloin.com/python-smooch
Author: Devin McGloin
Author-email: devin@devinmcgloin.com
License: MIT
Download-URL: https://github.com/devinmcgloin/python-smooch/tarball/v1.0.4
Keywords: messaging,smooch
Platform: UNKNOWN
Classifier: Development Status :: 5 - Production/Stable
Classifier: Intended Audience :: Developers
Classifier: Programming Language :: Python :: 2.6
Classifier: Programming Language :: Python :: 2.7
Classifier: Programming Language :: Python :: 3.3
Classifier: Programming Language :: Python :: 3.4
Classifier: Programming Language :: Python :: 3.5
Classifier: License :: OSI Approved :: MIT License
Classifier: Topic :: Communications :: Chat
Requires-Dist: requests
Requires-Dist: PyJWT
